ubelt/__init__.py
ubelt/__main__.py
ubelt/__main__.pyi
ubelt/_win32_jaraco.py
ubelt/_win32_links.py
ubelt/_win32_links.pyi
ubelt/orderedset.py
ubelt/orderedset.pyi
ubelt/progiter.py
ubelt/progiter.pyi
ubelt/py.typed
ubelt/util_arg.py
ubelt/util_arg.pyi
ubelt/util_cache.py
ubelt/util_cache.pyi
ubelt/util_cmd.py
ubelt/util_cmd.pyi
ubelt/util_colors.py
ubelt/util_colors.pyi
ubelt/util_const.py
ubelt/util_const.pyi
ubelt/util_deprecate.py
ubelt/util_deprecate.pyi
ubelt/util_dict.py
ubelt/util_dict.pyi
ubelt/util_download.py
ubelt/util_download.pyi
ubelt/util_download_manager.py
ubelt/util_download_manager.pyi
ubelt/util_format.py
ubelt/util_format.pyi
ubelt/util_func.py
ubelt/util_func.pyi
ubelt/util_futures.py
ubelt/util_futures.pyi
ubelt/util_hash.py
ubelt/util_hash.pyi
ubelt/util_import.py
ubelt/util_import.pyi
ubelt/util_indexable.py
ubelt/util_indexable.pyi
ubelt/util_io.py
ubelt/util_io.pyi
ubelt/util_links.py
ubelt/util_links.pyi
ubelt/util_list.py
ubelt/util_list.pyi
ubelt/util_memoize.py
ubelt/util_memoize.pyi
ubelt/util_mixins.py
ubelt/util_mixins.pyi
ubelt/util_path.py
ubelt/util_path.pyi
ubelt/util_platform.py
ubelt/util_platform.pyi
ubelt/util_repr.py
ubelt/util_repr.pyi
ubelt/util_str.py
ubelt/util_str.pyi
ubelt/util_stream.py
ubelt/util_stream.pyi
ubelt/util_time.py
ubelt/util_time.pyi
ubelt/util_zip.py
ubelt/util_zip.pyi
ubelt-1.3.8.dist-info/licenses/LICENSE
ubelt-1.3.8.dist-info/METADATA
ubelt-1.3.8.dist-info/WHEEL
ubelt-1.3.8.dist-info/top_level.txt
ubelt-1.3.8.dist-info/RECORD
